<dane_osobowe>
  <imie>Andrzej</imie>
  <nazwisko>Andrzej</nazwisko>
  <data_urodzenia>
    <dzien>12</dzien>
    <miesiac>02</miesiac>
    <rok>1984</rok>
  </data_urodzenia>
  <pesel>12345678901</pesel>
  <adres>
    <ulica>Słonecznikowa</ulica>
    <nr_domu>2</nr_domu>
    <nr_mieszkania>1</nr_mieszkania>
    <kod_pocztowy>11-200</kod_pocztowy>
    <miasto>Bartoszyce</miasto>
    <kraj kraj="Polska"/>
  </adres>
  <telefon>516235124</telefon>
  <email>dyrektor@clinic.eu</email>
</dane_osobowe>
